saaltfiish_boilerplate/__init__.py
saaltfiish_boilerplate/cli.py
saaltfiish_boilerplate/holidays.py
saaltfiish_boilerplate/instrument.py
saaltfiish_boilerplate/saaltfiish_boilerplate.py
saaltfiish_boilerplate-0.1.3.dist-info/AUTHORS.rst
saaltfiish_boilerplate-0.1.3.dist-info/LICENSE
saaltfiish_boilerplate-0.1.3.dist-info/METADATA
saaltfiish_boilerplate-0.1.3.dist-info/WHEEL
saaltfiish_boilerplate-0.1.3.dist-info/entry_points.txt
saaltfiish_boilerplate-0.1.3.dist-info/top_level.txt
saaltfiish_boilerplate-0.1.3.dist-info/RECORD
