Metadata-Version: 2.1
Name: saaltfiish-boilerplate
Version: 0.1.3
Summary: Python Boilerplate contains all the boilerplate you need to create a Python package.
Home-page: https://github.com/saaltfiish/saaltfiish_boilerplate
Author: saaltfiish
Author-email: ariuswho@outlook.com
License: MIT license
Keywords: saaltfiish_boilerplate
Platform: UNKNOWN
Classifier: Development Status :: 2 - Pre-Alpha
Classifier: Intended Audience :: Developers
Classifier: License :: OSI Approved :: MIT License
Classifier: Natural Language :: English
Classifier: Programming Language :: Python :: 3
Classifier: Programming Language :: Python :: 3.6
Classifier: Programming Language :: Python :: 3.7
Classifier: Programming Language :: Python :: 3.8
Requires-Python: >=3.6
License-File: LICENSE
License-File: AUTHORS.rst
